servus/__init__.py
servus/__utils.py
servus/discord_utils.py
servus/models.py
servus/requests.py
servus-1.0.0.dist-info/LICENSE
servus-1.0.0.dist-info/WHEEL
servus-1.0.0.dist-info/METADATA
servus-1.0.0.dist-info/RECORD
