Metadata-Version: 2.1
Name: servus
Version: 1.0.0
Summary: Human-friendly wrapper around the aiohttp library for making asynchronous web requests
Home-page: https://github.com/TheDynamics/servus
License: Apache 2.0 License
Keywords: async,asyncio,aiohttp,requests,web
Author: TobeTek
Author-email: katchyemma@gmail.com
Requires-Python: >=3.10,<4.0
Classifier: License :: OSI Approved :: Apache Software License
Classifier: License :: Other/Proprietary License
Classifier: Programming Language :: Python
Classifier: Programming Language :: Python :: 3
Classifier: Programming Language :: Python :: 3.10
Requires-Dist: aiohttp (>=3.6.0,<3.8.0)
Requires-Dist: discord.py (>=1.7.3,<2.0.0)
Project-URL: Documentation, https://TheDynamics.github.io/servus
Project-URL: Repository, https://github.com/TheDynamics/servus
